{
  "step": 1,
  "artifact_type": "procedure",
  "id": "PROC:WIN_Edita_Usuarios:Verifica_Menu_Solicitudes",
  "name": "Verifica_Menu_Solicitudes",
  "scope": "window_local",
  "owner_window": "WIN_Edita_Usuarios",
  "signature": "PROCEDURE Verifica_Menu_Solicitudes()",
  "output_dir": "docs/as-is/procedures/",
  "output_filename": "PROC_WIN_Edita_Usuarios_Verifica_Menu_Solicitudes.json",
  "tables_read": [],
  "tables_write": [],
  "relations_found": [],
  "metrics": {
    "lines": 198,
    "sql_fragments": 0
  },
  "wl_code": "gsResPath=TreeFind(TREE_Example, 1, Null, tvLeaf + tvNode)\nIF TREE_Example[gsResPath]..Checked=-1 THEN\nTREE_Example[gsResPath]..Checked=0\nEND\nIF TREE_Example[gsResPath]..Checked=0 THEN\ngsResPath=TreeFind(TREE_Example, 2, Null, tvLeaf + tvNode)\nTREE_Example[gsResPath]..Checked=0\ngsResPath=TreeFind(TREE_Example, 3, Null, tvLeaf + tvNode)\nTREE_Example[gsResPath]..Checked=0\ngsResPath=TreeFind(TREE_Example, 4, Null, tvLeaf + tvNode)\nTREE_Example[gsResPath]..Checked=0\ngsResPath=TreeFind(TREE_Example, 5, Null, tvLeaf + tvNode)\nTREE_Example[gsResPath]..Checked=0\ngsResPath=TreeFind(TREE_Example, 6, Null, tvLeaf + tvNode)\nTREE_Example[gsResPath]..Checked=0\ngsResPath=TreeFind(TREE_Example, 7, Null, tvLeaf + tvNode)\nTREE_Example[gsResPath]..Checked=0\ngsResPath=TreeFind(TREE_Example, 8, Null, tvLeaf + tvNode)\nTREE_Example[gsResPath]..Checked=0\ngsResPath=TreeFind(TREE_Example, 9, Null, tvLeaf + tvNode)\nTREE_Example[gsResPath]..Checked=0\ngsResPath=TreeFind(TREE_Example, 10, Null, tvLeaf + tvNode)\nTREE_Example[gsResPath]..Checked=0\ngsResPath=TreeFind(TREE_Example, 11, Null, tvLeaf + tvNode)\nTREE_Example[gsResPath]..Checked=0\ngsResPath=TreeFind(TREE_Example, 12, Null, tvLeaf + tvNode)\nTREE_Example[gsResPath]..Checked=0\ngsResPath=TreeFind(TREE_Example, 13, Null, tvLeaf + tvNode)\nTREE_Example[gsResPath]..Checked=0\ngsResPath=TreeFind(TREE_Example, 14, Null, tvLeaf + tvNode)\nTREE_Example[gsResPath]..Checked=0\ngsResPath=TreeFind(TREE_Example, 15, Null, tvLeaf + tvNode)\nTREE_Example[gsResPath]..Checked=0\ngsResPath=TreeFind(TREE_Example, 16, Null, tvLeaf + tvNode)\n\n\nPart 1 › WINDEV window › WIN_Edita_Usuarios › Procedures\n3/9/2026\n352\nSIATEC1_IA\nTREE_Example[gsResPath]..Checked=0\ngsResPath=TreeFind(TREE_Example, 17, Null, tvLeaf + tvNode)\nTREE_Example[gsResPath]..Checked=0\ngsResPath=TreeFind(TREE_Example, 18, Null, tvLeaf + tvNode)\nTREE_Example[gsResPath]..Checked=0\ngsResPath=TreeFind(TREE_Example, 19, Null, tvLeaf + tvNode)\nTREE_Example[gsResPath]..Checked=0\ngsResPath=TreeFind(TREE_Example, 20, Null, tvLeaf + tvNode)\nTREE_Example[gsResPath]..Checked=0\ngsResPath=TreeFind(TREE_Example, 21, Null, tvLeaf + tvNode)\nTREE_Example[gsResPath]..Checked=0\ngsResPath=TreeFind(TREE_Example, 22, Null, tvLeaf + tvNode)\nTREE_Example[gsResPath]..Checked=0\ngsResPath=TreeFind(TREE_Example, 23, Null, tvLeaf + tvNode)\nTREE_Example[gsResPath]..Checked=0\ngsResPath=TreeFind(TREE_Example, 24, Null, tvLeaf + tvNode)\nTREE_Example[gsResPath]..Checked=0\ngsResPath=TreeFind(TREE_Example, 25, Null, tvLeaf + tvNode)\nTREE_Example[gsResPath]..Checked=0\ngsResPath=TreeFind(TREE_Example, 26, Null, tvLeaf + tvNode)\nTREE_Example[gsResPath]..Checked=0\ngsResPath=TreeFind(TREE_Example, 27, Null, tvLeaf + tvNode)\nTREE_Example[gsResPath]..Checked=0\ngsResPath=TreeFind(TREE_Example, 28, Null, tvLeaf + tvNode)\nTREE_Example[gsResPath]..Checked=0\ngsResPath=TreeFind(TREE_Example, 29, Null, tvLeaf + tvNode)\nTREE_Example[gsResPath]..Checked=0\ngsResPath=TreeFind(TREE_Example, 30, Null, tvLeaf + tvNode)\nTREE_Example[gsResPath]..Checked=0\ngsResPath=TreeFind(TREE_Example, 31, Null, tvLeaf + tvNode)\nTREE_Example[gsResPath]..Checked=0\ngsResPath=TreeFind(TREE_Example, 32, Null, tvLeaf + tvNode)\nTREE_Example[gsResPath]..Checked=0\ngsResPath=TreeFind(TREE_Example, 33, Null, tvLeaf + tvNode)\nTREE_Example[gsResPath]..Checked=0\ngsResPath=TreeFind(TREE_Example, 34, Null, tvLeaf + tvNode)\nTREE_Example[gsResPath]..Checked=0\ngsResPath=TreeFind(TREE_Example, 35, Null, tvLeaf + tvNode)\nTREE_Example[gsResPath]..Checked=0\ngsResPath=TreeFind(TREE_Example, 36, Null, tvLeaf + tvNode)\nTREE_Example[gsResPath]..Checked=0\ngsResPath=TreeFind(TREE_Example, 37, Null, tvLeaf + tvNode)\nTREE_Example[gsResPath]..Checked=0\ngsResPath=TreeFind(TREE_Example, 38, Null, tvLeaf + tvNode)\nTREE_Example[gsResPath]..Checked=0\ngsResPath=TreeFind(TREE_Example, 39, Null, tvLeaf + tvNode)\nTREE_Example[gsResPath]..Checked=0\ngsResPath=TreeFind(TREE_Example, 40, Null, tvLeaf + tvNode)\nTREE_Example[gsResPath]..Checked=0\ngsResPath=TreeFind(TREE_Example, 41, Null, tvLeaf + tvNode)\nTREE_Example[gsResPath]..Checked=0\ngsResPath=TreeFind(TREE_Example, 42, Null, tvLeaf + tvNode)\nTREE_Example[gsResPath]..Checked=0\ngsResPath=TreeFind(TREE_Example, 43, Null, tvLeaf + tvNode)\nTREE_Example[gsResPath]..Checked=0\ngsResPath=TreeFind(TREE_Example, 44, Null, tvLeaf + tvNode)\nTREE_Example[gsResPath]..Checked=0\nELSE\ngsResPath=TreeFind(TREE_Example, 2, Null, tvLeaf + tvNode)\nTREE_Example[gsResPath]..Checked=1\ngsResPath=TreeFind(TREE_Example, 3, Null, tvLeaf + tvNode)\n\n\nPart 1 › WINDEV window › WIN_Edita_Usuarios › Procedures\n3/9/2026\n353\nSIATEC1_IA\nTREE_Example[gsResPath]..Checked=1\ngsResPath=TreeFind(TREE_Example, 4, Null, tvLeaf + tvNode)\nTREE_Example[gsResPath]..Checked=1\ngsResPath=TreeFind(TREE_Example, 5, Null, tvLeaf + tvNode)\nTREE_Example[gsResPath]..Checked=1\ngsResPath=TreeFind(TREE_Example, 6, Null, tvLeaf + tvNode)\nTREE_Example[gsResPath]..Checked=1\ngsResPath=TreeFind(TREE_Example, 7, Null, tvLeaf + tvNode)\nTREE_Example[gsResPath]..Checked=1\ngsResPath=TreeFind(TREE_Example, 8, Null, tvLeaf + tvNode)\nTREE_Example[gsResPath]..Checked=1\ngsResPath=TreeFind(TREE_Example, 9, Null, tvLeaf + tvNode)\nTREE_Example[gsResPath]..Checked=1\ngsResPath=TreeFind(TREE_Example, 10, Null, tvLeaf + tvNode)\nTREE_Example[gsResPath]..Checked=1\ngsResPath=TreeFind(TREE_Example, 11, Null, tvLeaf + tvNode)\nTREE_Example[gsResPath]..Checked=1\ngsResPath=TreeFind(TREE_Example, 12, Null, tvLeaf + tvNode)\nTREE_Example[gsResPath]..Checked=1\ngsResPath=TreeFind(TREE_Example, 13, Null, tvLeaf + tvNode)\nTREE_Example[gsResPath]..Checked=1\ngsResPath=TreeFind(TREE_Example, 14, Null, tvLeaf + tvNode)\nTREE_Example[gsResPath]..Checked=1\ngsResPath=TreeFind(TREE_Example, 15, Null, tvLeaf + tvNode)\nTREE_Example[gsResPath]..Checked=1\ngsResPath=TreeFind(TREE_Example, 16, Null, tvLeaf + tvNode)\nTREE_Example[gsResPath]..Checked=1\ngsResPath=TreeFind(TREE_Example, 17, Null, tvLeaf + tvNode)\nTREE_Example[gsResPath]..Checked=1\ngsResPath=TreeFind(TREE_Example, 18, Null, tvLeaf + tvNode)\nTREE_Example[gsResPath]..Checked=1\ngsResPath=TreeFind(TREE_Example, 19, Null, tvLeaf + tvNode)\nTREE_Example[gsResPath]..Checked=1\ngsResPath=TreeFind(TREE_Example, 20, Null, tvLeaf + tvNode)\nTREE_Example[gsResPath]..Checked=1\ngsResPath=TreeFind(TREE_Example, 21, Null, tvLeaf + tvNode)\nTREE_Example[gsResPath]..Checked=1\ngsResPath=TreeFind(TREE_Example, 22, Null, tvLeaf + tvNode)\nTREE_Example[gsResPath]..Checked=1\ngsResPath=TreeFind(TREE_Example, 23, Null, tvLeaf + tvNode)\nTREE_Example[gsResPath]..Checked=1\ngsResPath=TreeFind(TREE_Example, 24, Null, tvLeaf + tvNode)\nTREE_Example[gsResPath]..Checked=1\ngsResPath=TreeFind(TREE_Example, 25, Null, tvLeaf + tvNode)\nTREE_Example[gsResPath]..Checked=1\ngsResPath=TreeFind(TREE_Example, 26, Null, tvLeaf + tvNode)\nTREE_Example[gsResPath]..Checked=1\ngsResPath=TreeFind(TREE_Example, 27, Null, tvLeaf + tvNode)\nTREE_Example[gsResPath]..Checked=1\ngsResPath=TreeFind(TREE_Example, 28, Null, tvLeaf + tvNode)\nTREE_Example[gsResPath]..Checked=1\ngsResPath=TreeFind(TREE_Example, 29, Null, tvLeaf + tvNode)\nTREE_Example[gsResPath]..Checked=1\ngsResPath=TreeFind(TREE_Example, 30, Null, tvLeaf + tvNode)\nTREE_Example[gsResPath]..Checked=1\ngsResPath=TreeFind(TREE_Example, 31, Null, tvLeaf + tvNode)\nTREE_Example[gsResPath]..Checked=1\ngsResPath=TreeFind(TREE_Example, 32, Null, tvLeaf + tvNode)\nTREE_Example[gsResPath]..Checked=1\ngsResPath=TreeFind(TREE_Example, 33, Null, tvLeaf + tvNode)\nTREE_Example[gsResPath]..Checked=1\n\n\nPart 1 › WINDEV window › WIN_Edita_Usuarios › Procedures\n3/9/2026\n354\nSIATEC1_IA\ngsResPath=TreeFind(TREE_Example, 34, Null, tvLeaf + tvNode)\nTREE_Example[gsResPath]..Checked=1\ngsResPath=TreeFind(TREE_Example, 35, Null, tvLeaf + tvNode)\nTREE_Example[gsResPath]..Checked=1\ngsResPath=TreeFind(TREE_Example, 36, Null, tvLeaf + tvNode)\nTREE_Example[gsResPath]..Checked=1\ngsResPath=TreeFind(TREE_Example, 37, Null, tvLeaf + tvNode)\nTREE_Example[gsResPath]..Checked=1\ngsResPath=TreeFind(TREE_Example, 38, Null, tvLeaf + tvNode)\nTREE_Example[gsResPath]..Checked=1\ngsResPath=TreeFind(TREE_Example, 39, Null, tvLeaf + tvNode)\nTREE_Example[gsResPath]..Checked=1\ngsResPath=TreeFind(TREE_Example, 40, Null, tvLeaf + tvNode)\nTREE_Example[gsResPath]..Checked=1\ngsResPath=TreeFind(TREE_Example, 41, Null, tvLeaf + tvNode)\nTREE_Example[gsResPath]..Checked=1\ngsResPath=TreeFind(TREE_Example, 42, Null, tvLeaf + tvNode)\nTREE_Example[gsResPath]..Checked=1\ngsResPath=TreeFind(TREE_Example, 43, Null, tvLeaf + tvNode)\nTREE_Example[gsResPath]..Checked=1\ngsResPath=TreeFind(TREE_Example, 44, Null, tvLeaf + tvNode)\nTREE_Example[gsResPath]..Checked=1\nEND\nLocal procedure Verifica_MenuPrgBien"
}